<?xml version="1.0" ?>

<container xmlns="http://symfony.com/schema/dic/services"
           xmlns:xsi="http://www.w3.org/2001/XMLSchema-instance"
           xsi:schemaLocation="http://symfony.com/schema/dic/services http://symfony.com/schema/dic/services/services-1.0.xsd">

    <services>
        <defaults autowire="true" autoconfigure="true"/>
        <prototype namespace="SptecOrderComments\" resource="../../" exclude="../../{DependencyInjection,Resources,Migration,SptecOrderComments.php}" />

        <!-- Explicitly register entity extensions -->
        <service id="SptecOrderComments\Extension\Checkout\Order\OrderComment\OrderCommentExtension">
            <tag name="shopware.entity.extension"/>
        </service>

        <service id="SptecOrderComments\Extension\Content\Media\MediaExtension">
            <tag name="shopware.entity.extension"/>
        </service>

        <service id="SptecOrderComments\Extension\System\User\UserExtension">
            <tag name="shopware.entity.extension"/>
        </service>

        <!-- Explicitly register entity definitions -->
        <service id="SptecOrderComments\Extension\Checkout\Order\OrderComment\OrderCommentDefinition">
            <tag name="shopware.entity.definition"/>
        </service>

        <service id="SptecOrderComments\Extension\Checkout\Order\OrderComment\OrderCommentMediaDefinition">
            <tag name="shopware.entity.definition"/>
        </service>
    </services>
</container>